analog/__init__.py
analog/define.py
analog/exceptions.py
analog/models.py
analog/settings.py
analog/util.py
django_analog-2.0.0.dist-info/LICENSE
django_analog-2.0.0.dist-info/METADATA
django_analog-2.0.0.dist-info/WHEEL
django_analog-2.0.0.dist-info/top_level.txt
django_analog-2.0.0.dist-info/RECORD
