Metadata-Version: 2.1
Name: django-analog
Version: 2.0.0
Summary: Simple per-model log models for Django apps
Home-page: https://github.com/andersinno/django-analog
Author: Anders Innovations
Author-email: support@anders.fi
License: MIT
Keywords: django,logging
Platform: any
Requires-Dist: Django
